osscar_voila-0.2.9.data/data/etc/jupyter/jupyter_notebook_config.d/voila.json
osscar_voila-0.2.9.data/data/etc/jupyter/jupyter_server_config.d/voila.json
osscar_voila-0.2.9.data/data/etc/jupyter/nbconfig/notebook.d/voila.json
osscar_voila-0.2.9.data/data/share/jupyter/labextensions/@voila-dashboards/jupyterlab-preview/install.json
osscar_voila-0.2.9.data/data/share/jupyter/labextensions/@voila-dashboards/jupyterlab-preview/package.json
osscar_voila-0.2.9.data/data/share/jupyter/labextensions/@voila-dashboards/jupyterlab-preview/schemas/@voila-dashboards/jupyterlab-preview/package.json.orig
osscar_voila-0.2.9.data/data/share/jupyter/labextensions/@voila-dashboards/jupyterlab-preview/schemas/@voila-dashboards/jupyterlab-preview/plugin.json
osscar_voila-0.2.9.data/data/share/jupyter/labextensions/@voila-dashboards/jupyterlab-preview/static/776.5a65bd8d418bae34dfbf.js
osscar_voila-0.2.9.data/data/share/jupyter/labextensions/@voila-dashboards/jupyterlab-preview/static/925.454db0615e72f3847e2a.js
osscar_voila-0.2.9.data/data/share/jupyter/labextensions/@voila-dashboards/jupyterlab-preview/static/remoteEntry.f25cd0dfaba30f8565b7.js
osscar_voila-0.2.9.data/data/share/jupyter/labextensions/@voila-dashboards/jupyterlab-preview/static/style.js
osscar_voila-0.2.9.data/data/share/jupyter/nbextensions/voila/extension.js
osscar_voila-0.2.9.data/data/share/jupyter/voila/templates/base/404.html
osscar_voila-0.2.9.data/data/share/jupyter/voila/templates/base/browser-open.html
osscar_voila-0.2.9.data/data/share/jupyter/voila/templates/base/error.html
osscar_voila-0.2.9.data/data/share/jupyter/voila/templates/base/jupyter_widgets.html.j2
osscar_voila-0.2.9.data/data/share/jupyter/voila/templates/base/log.macro.html.j2
osscar_voila-0.2.9.data/data/share/jupyter/voila/templates/base/page.html
osscar_voila-0.2.9.data/data/share/jupyter/voila/templates/base/spinner.macro.html.j2
osscar_voila-0.2.9.data/data/share/jupyter/voila/templates/base/tree.html
osscar_voila-0.2.9.dist-info/LICENSE
osscar_voila-0.2.9.dist-info/METADATA
osscar_voila-0.2.9.dist-info/WHEEL
osscar_voila-0.2.9.dist-info/entry_points.txt
osscar_voila-0.2.9.dist-info/top_level.txt
osscar_voila-0.2.9.dist-info/RECORD
