Metadata-Version: 2.1
Name: osscar-voila
Version: 0.2.9
Summary: Voilà turns Jupyter notebooks into standalone web applications
Home-page: https://github.com/voila-dashboards/voila
Author: Voila Development Team
Author-email: jupyter@googlegroups.com
License: BSD-3-Clause
Keywords: Jupyter,JupyterLab,Voila
Platform: Linux
Platform: Mac OS X
Platform: Windows
Classifier: License :: OSI Approved :: BSD License
Classifier: Programming Language :: Python
Classifier: Programming Language :: Python :: 3
Classifier: Programming Language :: Python :: 3.6
Classifier: Programming Language :: Python :: 3.7
Classifier: Programming Language :: Python :: 3.8
Classifier: Programming Language :: Python :: 3.9
Classifier: Framework :: Jupyter
Requires-Python: >=3.6
Requires-Dist: jupyter-server (<2.0.0,>=0.3.0)
Requires-Dist: jupyter-client (<7,>=6.1.3)
Requires-Dist: nbclient (<0.6,>=0.4.0)
Requires-Dist: nbconvert (<7,>=6.0.0)
Provides-Extra: test
Requires-Dist: ipywidgets ; extra == 'test'
Requires-Dist: mock ; extra == 'test'
Requires-Dist: matplotlib ; extra == 'test'
Requires-Dist: pytest ; extra == 'test'
Requires-Dist: pytest-tornasync ; extra == 'test'
